jiten/__init__.py
jiten/app.py
jiten/cli.py
jiten/freq.py
jiten/jmdict.py
jiten/kanji.py
jiten/misc.py
jiten/sql.py
jiten/res/freq/SOURCES
jiten/res/freq/base_aggregates.txt.nobom
jiten/res/freq/wordfreq_ck.utf8
jiten/res/jmdict/jmdict.xml.gz
jiten/res/jmdict/kanjidic2.xml.gz
jiten/res/jmdict/licence.html
jiten/static/Table_hiragana.svg
jiten/static/Table_katakana.svg
jiten/static/bootstrap-darkly.min.css
jiten/static/bootstrap-flatly.min.css
jiten/static/bootstrap.min.css
jiten/static/bootstrap.min.js
jiten/static/jquery-3.5.1.slim.min.js
jiten/static/popper-1.16.0.min.js
jiten/static/script.js
jiten/static/style.css
jiten/static/font/KanjiStrokeOrders_v4.001.ttf
jiten/static/font/copyright.txt
jiten/static/font/readme_en_v4.001.txt
jiten/templates/_footer.html
jiten/templates/_meta.html
jiten/templates/_nav.html
jiten/templates/_search.html
jiten/templates/index.html
jiten/templates/jmdict-by-freq.html
jiten/templates/jmdict.html
jiten/templates/kanji-by-freq.html
jiten/templates/kanji-by-level.html
jiten/templates/kanji.html
jiten/templates/stroke.html
jiten-0.1.1.data/scripts/jiten
jiten-0.1.1.dist-info/LICENSE.AGPLv3
jiten-0.1.1.dist-info/METADATA
jiten-0.1.1.dist-info/WHEEL
jiten-0.1.1.dist-info/top_level.txt
jiten-0.1.1.dist-info/RECORD
