Metadata-Version: 2.1
Name: jiten
Version: 0.1.1
Summary: japanese cli&web dictionary based on jmdict/kanjidic
Home-page: https://github.com/obfusk/jiten
Author: Felix C. Stegerman
Author-email: flx@obfusk.net
License: AGPLv3+
Keywords: japanese kanji dictionary cli web jmdict kanjidic
Platform: UNKNOWN
Classifier: Development Status :: 4 - Beta
Classifier: Environment :: Console
Classifier: Environment :: Web Environment
Classifier: Intended Audience :: End Users/Desktop
Classifier: License :: OSI Approved :: GNU Affero General Public License v3 or later (AGPLv3+)
Classifier: Natural Language :: Dutch
Classifier: Natural Language :: English
Classifier: Natural Language :: German
Classifier: Natural Language :: Japanese
Classifier: Operating System :: POSIX :: Linux
Classifier: Programming Language :: Python :: 3
Classifier: Programming Language :: Python :: 3.5
Classifier: Programming Language :: Python :: 3.6
Classifier: Programming Language :: Python :: 3.7
Classifier: Programming Language :: Python :: 3.8
Classifier: Programming Language :: Python :: Implementation :: CPython
Classifier: Topic :: Education
Classifier: Topic :: Utilities
Requires-Python: >=3.5
Requires-Dist: Flask
Requires-Dist: click (>=6.0)
